<?xml version="1.0" ?>
<Component>
  <Name>RC</Name>
  <Description>RAM Controller for tmpm361</Description>
  <Category>Peripheral</Category>
  <Version>1.200</Version>
  <Tags>RC</Tags>
  
  <files>
    <File>$REPO_ROOT$\TMPM36x\TMPM361\cmsis_lib\lib\include\tmpm361_rc.h</File>
    <File>$REPO_ROOT$\TMPM36x\TMPM361\cmsis_lib\lib\source\tmpm361_rc.c</File>
  </files>
  
  <CoIDEFiles>
    <File>$PROJECT_ROOT$\cmsis_lib\include\tmpm361_rc.h</File>
    <File>$PROJECT_ROOT$\cmsis_lib\source\tmpm361_rc.c</File>
  </CoIDEFiles>
  
  <Dependencys>
    <Dependency>CMSIS_BOOT</Dependency>
  </Dependencys>
  
  <SupportDevices>
    <Device>TMPM361F10FG,TMPM361FDFG,TMPM361FYFG</Device>
  </SupportDevices>

</Component>